pprogress/__init__.py
pprogress/progress.py
PProgress-0.0.5.dist-info/LICENSE
PProgress-0.0.5.dist-info/METADATA
PProgress-0.0.5.dist-info/WHEEL
PProgress-0.0.5.dist-info/top_level.txt
PProgress-0.0.5.dist-info/RECORD
