Metadata-Version: 2.1
Name: PProgress
Version: 0.0.5
Summary: Simple Python progress bar for parallel programs.
Home-page: UNKNOWN
Author: Fergus Horrobin
Author-email: fergus.horrobin@mail.utoronto.ca
License: GPL
Platform: UNKNOWN
